smartcitizen_connector/__init__.py
smartcitizen_connector/_config/__init__.py
smartcitizen_connector/_config/config.py
smartcitizen_connector/device/__init__.py
smartcitizen_connector/device/device.py
smartcitizen_connector/experiment/__init__.py
smartcitizen_connector/experiment/experiment.py
smartcitizen_connector/handler/__init__.py
smartcitizen_connector/handler/httphandler.py
smartcitizen_connector/measurement/__init__.py
smartcitizen_connector/measurement/measurement.py
smartcitizen_connector/models/__init__.py
smartcitizen_connector/models/models.py
smartcitizen_connector/search/__init__.py
smartcitizen_connector/search/search.py
smartcitizen_connector/sensor/__init__.py
smartcitizen_connector/sensor/sensor.py
smartcitizen_connector/tools/__init__.py
smartcitizen_connector/tools/tools.py
smartcitizen_connector/user/__init__.py
smartcitizen_connector/user/user.py
smartcitizen_connector-1.3.4.dist-info/licenses/LICENSE
smartcitizen_connector-1.3.4.dist-info/METADATA
smartcitizen_connector-1.3.4.dist-info/WHEEL
smartcitizen_connector-1.3.4.dist-info/top_level.txt
smartcitizen_connector-1.3.4.dist-info/RECORD
