Metadata-Version: 2.4
Name: smartcitizen-connector
Version: 1.3.4
Summary: Python connector to download information collected in SmartCitizen API
Home-page: https://github.com/fablabbcn/smartcitizen-connector
Author: oscgonfer
License: GNU General Public License v3
Project-URL: Documentation, https://docs.smartcitizen.me/
Project-URL: Source Code, https://github.com/fablabbcn/smartcitizen-connector
Keywords: sensors,Smart Citizen
Classifier: Development Status :: 4 - Beta
Classifier: Intended Audience :: Education
Classifier: Intended Audience :: Science/Research
Classifier: Intended Audience :: Developers
Classifier: License :: OSI Approved :: GNU General Public License v3 or later (GPLv3+)
Classifier: Operating System :: Unix
Classifier: Operating System :: POSIX
Classifier: Programming Language :: Python
Classifier: Programming Language :: Python :: 3
Classifier: Programming Language :: Python :: 3.8
Classifier: Programming Language :: Python :: 3.9
Classifier: Programming Language :: Python :: 3.10
Classifier: Programming Language :: Python :: 3.11
Classifier: Programming Language :: Python :: 3.12
Classifier: Topic :: Utilities
Classifier: Natural Language :: English
Requires-Python: >=3.8
License-File: LICENSE
Requires-Dist: pydantic
Requires-Dist: requests
Requires-Dist: pandas
Requires-Dist: timezonefinder
Requires-Dist: urllib3
Requires-Dist: aiohttp
Requires-Dist: aiohttp-retry
Requires-Dist: termcolor
Requires-Dist: tqdm
Dynamic: author
Dynamic: classifier
Dynamic: description
Dynamic: description-content-type
Dynamic: home-page
Dynamic: keywords
Dynamic: license
Dynamic: license-file
Dynamic: project-url
Dynamic: requires-dist
Dynamic: requires-python
Dynamic: summary
